digole.py
digole-0.0.5.dist-info/LICENSE
digole-0.0.5.dist-info/METADATA
digole-0.0.5.dist-info/WHEEL
digole-0.0.5.dist-info/top_level.txt
digole-0.0.5.dist-info/RECORD
