Metadata-Version: 2.1
Name: digole
Version: 0.0.5
Summary: Digole LCD Drivers
Home-page: https://github.com/jethornton/digole
Author: John Thornton
Author-email: bjt128@gmail.com
License: MIT License
Platform: UNKNOWN
Classifier: Programming Language :: Python :: 3
Classifier: License :: OSI Approved :: MIT License
Classifier: Operating System :: POSIX :: Linux
Requires-Dist: smbus2
